ontorunner/__init__.py
ontorunner/converters/__init__.py
ontorunner/converters/biohub_converter.py
ontorunner/oger_module.py
ontorunner/pipes/OntoRuler.py
ontorunner/pipes/__init__.py
ontorunner/post/__init__.py
ontorunner/post/add_sentence.py
ontorunner/post/util.py
ontorunner/pre/__init__.py
ontorunner/pre/util.py
ontorunner/settings.ini
ontorunner/spacy_module.py
ontorunner-0.1.3.dist-info/entry_points.txt
ontorunner-0.1.3.dist-info/LICENSE
ontorunner-0.1.3.dist-info/WHEEL
ontorunner-0.1.3.dist-info/METADATA
ontorunner-0.1.3.dist-info/RECORD
