Metadata-Version: 2.1
Name: ontorunner
Version: 0.1.3
Summary: This is a wrapper project around various entity recognition (NER) tools.
License: MIT
Author: Harshad Hegde
Author-email: hhegde@lbl.gov
Requires-Python: >=3.8,<4.0
Classifier: License :: OSI Approved :: MIT License
Classifier: Programming Language :: Python :: 3
Classifier: Programming Language :: Python :: 3.10
Classifier: Programming Language :: Python :: 3.8
Classifier: Programming Language :: Python :: 3.9
Provides-Extra: docs
Requires-Dist: CairoSVG (>=2.5.2,<3.0.0)
Requires-Dist: OGER (>=1.5,<2.0)
Requires-Dist: click (>=8.1.3,<9.0.0)
Requires-Dist: dframcy (>=0.1.6,<0.2.0)
Requires-Dist: kgx (>=1.5.8,<2.0.0)
Requires-Dist: pandas (>=1.4.2,<2.0.0)
Requires-Dist: scispacy (==0.5.0)
Requires-Dist: six (>=1.16.0,<2.0.0)
Requires-Dist: spacy (>=3.2.0,<3.3.0)
Requires-Dist: textdistance[extras] (>=4.2.2,<5.0.0)
